rl_tetris/__init__.py
rl_tetris/envs/__init__.py
rl_tetris/envs/tetris.py
rl_tetris/game_state.py
rl_tetris/mapping/__init__.py
rl_tetris/mapping/actions.py
rl_tetris/randomizer.py
rl_tetris/renderer.py
rl_tetris/tetromino_queue.py
rl_tetris/wrapper/Grouped.py
rl_tetris/wrapper/Observation.py
rl_tetris/wrapper/__init__.py
rl_tetris-0.2.2.dist-info/LICENSE
rl_tetris-0.2.2.dist-info/METADATA
rl_tetris-0.2.2.dist-info/WHEEL
rl_tetris-0.2.2.dist-info/RECORD
